{"parameters_list": [{"moving_dot_brightness": 1.0, "radius": 10.0, "moving_dot_init_x_pos": 0.0, "moving_dot_init_y_pos": 0.0, "v_y": 0.0, "v_x": 20.0, "background_brightness": 0.0}, {"velocity": 5.0, "angle": 0.0, "init_phase": 0.0, "merging_pos": 0.5, "brightness": 1.0, "contrast": 1.0, "frequency": 0.20000000000000001}], "TTL_params": {"frequency": 50.0, "pulse_width": 1.0, "duration": 5.0, "delay": 10.0}, "types_list": ["Moving Dot", "Optomotor Grating"], "durations_list": [10.0, 10.0], "stim_list": ["Stim 1", "Stim 2"]}